{
    "version": "0.4",
    "title": "404 Page",
    "type": "section",
    "metadata": {
        "template_type": "single-404",
        "include_in_zip": "1",
        "elementor_pro_required": null,
        "wp_page_template": "elementor_header_footer"
    },
    "content": [
        {
            "id": "78ce80eb",
            "settings": {
                "content_width": {
                    "unit": "px",
                    "size": 1200,
                    "sizes": []
                },
                "height": "full",
                "structure": "20",
                "background_overlay_background": "classic",
                "background_overlay_image": {
                    "url": "http:\/\/askproject.net\/exela\/wp-content\/uploads\/sites\/59\/2022\/03\/black-and-white-30.jpg",
                    "id": 204,
                    "alt": "",
                    "source": "library"
                },
                "background_overlay_position": "center center",
                "background_overlay_size": "cover",
                "background_overlay_opacity": {
                    "unit": "px",
                    "size": 0.15,
                    "sizes": []
                },
                "padding": {
                    "unit": "px",
                    "top": "30",
                    "right": "0",
                    "bottom": "0",
                    "left": "0",
                    "isLinked": false
                },
                "padding_tablet": {
                    "unit": "px",
                    "top": "100",
                    "right": "30",
                    "bottom": "50",
                    "left": "30",
                    "isLinked": false
                },
                "padding_mobile": {
                    "unit": "px",
                    "top": "120",
                    "right": "20",
                    "bottom": "60",
                    "left": "20",
                    "isLinked": false
                },
                "__globals__": {
                    "background_color": "globals\/colors?id=secondary"
                }
            },
            "elements": [
                {
                    "id": "35d72283",
                    "settings": {
                        "_column_size": 50,
                        "_inline_size": 45,
                        "_inline_size_tablet": 100,
                        "padding": {
                            "unit": "px",
                            "top": "0",
                            "right": "0",
                            "bottom": "0",
                            "left": "0",
                            "isLinked": false
                        },
                        "padding_mobile": {
                            "unit": "px",
                            "top": "0",
                            "right": "0",
                            "bottom": "50",
                            "left": "0",
                            "isLinked": false
                        }
                    },
                    "elements": [
                        {
                            "id": "297a7d97",
                            "settings": {
                                "image": {
                                    "url": "http:\/\/askproject.net\/exela\/wp-content\/uploads\/sites\/59\/2022\/03\/404_Asset-11.png",
                                    "id": 723,
                                    "alt": "",
                                    "source": "library"
                                },
                                "width_tablet": {
                                    "unit": "%",
                                    "size": 40,
                                    "sizes": []
                                },
                                "width_mobile": {
                                    "unit": "%",
                                    "size": 60,
                                    "sizes": []
                                },
                                "hover_animation": "float",
                                "_animation": "fadeIn"
                            },
                            "elements": [],
                            "isInner": false,
                            "widgetType": "image",
                            "elType": "widget"
                        }
                    ],
                    "isInner": false,
                    "elType": "column"
                },
                {
                    "id": "55afd68d",
                    "settings": {
                        "_column_size": 50,
                        "_inline_size": 55,
                        "_inline_size_tablet": 100,
                        "padding": {
                            "unit": "px",
                            "top": "0",
                            "right": "0",
                            "bottom": "0",
                            "left": "100",
                            "isLinked": false
                        },
                        "padding_tablet": {
                            "unit": "px",
                            "top": "0",
                            "right": "0",
                            "bottom": "0",
                            "left": "0",
                            "isLinked": false
                        }
                    },
                    "elements": [
                        {
                            "id": "7b7c0b71",
                            "settings": {
                                "image": {
                                    "url": "http:\/\/askproject.net\/exela\/wp-content\/uploads\/sites\/59\/2022\/03\/404_Asset-8.png",
                                    "id": 718,
                                    "alt": "",
                                    "source": "library"
                                },
                                "align": "left",
                                "align_tablet": "center",
                                "width": {
                                    "unit": "%",
                                    "size": 45,
                                    "sizes": []
                                },
                                "width_tablet": {
                                    "unit": "%",
                                    "size": 35,
                                    "sizes": []
                                },
                                "width_mobile": {
                                    "unit": "%",
                                    "size": 65,
                                    "sizes": []
                                },
                                "_animation": "fadeInUp"
                            },
                            "elements": [],
                            "isInner": false,
                            "widgetType": "image",
                            "elType": "widget"
                        },
                        {
                            "id": "59c09a46",
                            "settings": {
                                "title": "Oops! Page not found!",
                                "align_tablet": "center",
                                "_animation": "fadeInUp",
                                "_animation_delay": 200
                            },
                            "elements": [],
                            "isInner": false,
                            "widgetType": "heading",
                            "elType": "widget"
                        },
                        {
                            "id": "430e6968",
                            "settings": {
                                "align_tablet": "center",
                                "_margin_tablet": {
                                    "unit": "px",
                                    "top": "0",
                                    "right": "90",
                                    "bottom": "0",
                                    "left": "90",
                                    "isLinked": false
                                },
                                "_margin_mobile": {
                                    "unit": "px",
                                    "top": "0",
                                    "right": "0",
                                    "bottom": "0",
                                    "left": "0",
                                    "isLinked": false
                                },
                                "_animation": "fadeInUp",
                                "_animation_delay": 400
                            },
                            "elements": [],
                            "isInner": false,
                            "widgetType": "text-editor",
                            "elType": "widget"
                        },
                        {
                            "id": "e2d12b0",
                            "settings": {
                                "text": "Back to Homepage",
                                "align": "left",
                                "button_text_color": "#FFFFFF",
                                "border_radius": {
                                    "unit": "px",
                                    "top": "50",
                                    "right": "50",
                                    "bottom": "50",
                                    "left": "50",
                                    "isLinked": true
                                },
                                "text_padding": {
                                    "unit": "px",
                                    "top": "15",
                                    "right": "35",
                                    "bottom": "15",
                                    "left": "35",
                                    "isLinked": false
                                },
                                "__globals__": {
                                    "background_color": "globals\/colors?id=primary",
                                    "button_background_hover_color": "globals\/colors?id=accent",
                                    "typography_typography": "globals\/typography?id=accent"
                                },
                                "_animation": "fadeInUp",
                                "_animation_delay": 600,
                                "align_tablet": "center"
                            },
                            "elements": [],
                            "isInner": false,
                            "widgetType": "button",
                            "elType": "widget"
                        }
                    ],
                    "isInner": false,
                    "elType": "column"
                }
            ],
            "isInner": false,
            "elType": "section"
        }
    ],
    "page_settings": {
        "hide_title": "yes",
        "template": "elementor_header_footer"
    }
}